{
  "id": "I3E5642AB",
  "title": {
    "bo": "དབུ་མ་ལ་འཇུག་པའི་རྣམ་པར་བཤད་པ་ངེས་དོན་གནད་ཀྱི་ཊཱི་ཀ",
    "en": "A Detailed Explanation of the Definitive Meaning, A Commentary on Entering the Middle Way"
  },
  "author": {
    "bo": "པཎ་ཆེན་ཤཱཀྱ་མཆོག་ལྡན།",
    "en": "None"
  },
  "imported": "2025-02-07T14:55:54.807655",
  "source": "https://library.bdrc.io/show/bdr:WA20401?tabs=bdr:MW20401,bdr:W20401",
  "toolkit_version": "0.0.1",
  "parser": "DocxNumberListCommentaryParser",
  "initial_creation_type": "google_docx",
  "language": "bo",
  "source_metadata": {
    "document_id": "1YYBQvjUFebixt22C6Zq6kLYMLbBCj70hCffCMAR2clQ",
    "commentary_alignments": [
      {
        "source": "I7A5C542E/layers/8921/Tibetan_Segment-8743.json",
        "target": "I3E5642AB/layers/86EE/Meaning_Segment-91D9.json"
      }
    ],
    "long_title": {
      "bo": "དབུ་མ་ལ་འཇུག་པའི་རྣམ་པར་བཤད་པ་ངེས་དོན་གནད་ཀྱི་ཊཱི་ཀ",
      "en": "A Detailed Explanation of the Definitive Meaning, A Commentary on Entering the Middle Way"
    },
    "presentation": {
      "en": ""
    },
    "usage_title": {
      "bo": "དབུ་མ་ལ་འཇུག་པའི་རྣམ་པར་བཤད་པ་ངེས་དོན་གནད་ཀྱི་ཊཱི་ཀ",
      "en": "A Detailed Explanation of the Definitive Meaning, A Commentary on Entering the Middle Way"
    },
    "commentary_of": "I7A5C542E"
  },
  "bases": [],
  "copyright": {
    "status": "Unknown",
    "notice": "",
    "info_url": null
  },
  "licence": "Unknown"
}